[
  {
    "topic": "sports news",
    "title": "Inter Milan reach Champions League final after beating Barcelona 🤯",
    "videoId": "YO25dOMaog0",
    "thumbnail": "https://i.ytimg.com/vi/YO25dOMaog0/mqdefault.jpg",
    "publishedAt": "2025-05-06T22:19:56Z"
  },
  {
    "topic": "sports news",
    "title": "Can Inter Milan stop Lamine Yamal?",
    "videoId": "9VpOY1PnlSE",
    "thumbnail": "https://i.ytimg.com/vi/9VpOY1PnlSE/mqdefault.jpg",
    "publishedAt": "2025-05-06T14:00:13Z"
  },
  {
    "topic": "sports news",
    "title": "&quot;I&#39;m not angry, I&#39;m disappointed&quot; | Carra&#39;s HONEST opinion on Alexander-Arnold leaving Liverpool",
    "videoId": "Cephg09IBcQ",
    "thumbnail": "https://i.ytimg.com/vi/Cephg09IBcQ/mqdefault.jpg",
    "publishedAt": "2025-05-05T18:30:36Z"
  },
  {
    "topic": "sports news",
    "title": "BREAKING: Trent Alexander-Arnold to leave Liverpool",
    "videoId": "_F3Q3rDfrNw",
    "thumbnail": "https://i.ytimg.com/vi/_F3Q3rDfrNw/mqdefault.jpg",
    "publishedAt": "2025-05-05T09:23:42Z"
  },
  {
    "topic": "sports news",
    "title": "খেলাযোগ, ৬ মে ২০২৫ | Sports News | Khelajog",
    "videoId": "HtPYtwma610",
    "thumbnail": "https://i.ytimg.com/vi/HtPYtwma610/mqdefault.jpg",
    "publishedAt": "2025-05-06T17:11:11Z"
  },
  {
    "topic": "world news",
    "title": "ABC World News Tonight with David Muir Full Broadcast - May 6, 2025",
    "videoId": "QzpPdmSTXBc",
    "thumbnail": "https://i.ytimg.com/vi/QzpPdmSTXBc/mqdefault.jpg",
    "publishedAt": "2025-05-07T01:45:01Z"
  },
  {
    "topic": "world news",
    "title": "India fires several missiles at &#39;terrorist infrastructure&#39; in Pakistan, India says",
    "videoId": "x4haKPc65R0",
    "thumbnail": "https://i.ytimg.com/vi/x4haKPc65R0/mqdefault.jpg",
    "publishedAt": "2025-05-06T21:16:41Z"
  },
  {
    "topic": "world news",
    "title": "India launches airstrikes on Pakistan and Pakistan-administered Kashmir | BBC News",
    "videoId": "t90rjAt-4EE",
    "thumbnail": "https://i.ytimg.com/vi/t90rjAt-4EE/mqdefault.jpg",
    "publishedAt": "2025-05-07T09:37:37Z"
  },
  {
    "topic": "world news",
    "title": "Canada &#39;not for sale, ever&#39;, Canadian PM Carney warns Trump | BBC News",
    "videoId": "K9WlTAlsvkc",
    "thumbnail": "https://i.ytimg.com/vi/K9WlTAlsvkc/mqdefault.jpg",
    "publishedAt": "2025-05-06T18:32:29Z"
  },
  {
    "topic": "world news",
    "title": "India Strikes Pakistan: How Media In US, Russia, China, Iran, Israel Reported &#39;Op Sindoor&#39;| Pahalgam",
    "videoId": "C-Le66qqEZk",
    "thumbnail": "https://i.ytimg.com/vi/C-Le66qqEZk/mqdefault.jpg",
    "publishedAt": "2025-05-07T04:05:22Z"
  },
  {
    "topic": "technology",
    "title": "Is this an iPhone KILLER😳#tech",
    "videoId": "PBmrLVBH9OI",
    "thumbnail": "https://i.ytimg.com/vi/PBmrLVBH9OI/mqdefault.jpg",
    "publishedAt": "2024-12-08T21:36:50Z"
  },
  {
    "topic": "technology",
    "title": "5 ILLEGAL gadgets that will get you ARRESTED",
    "videoId": "1Nef8LPO-jo",
    "thumbnail": "https://i.ytimg.com/vi/1Nef8LPO-jo/mqdefault.jpg",
    "publishedAt": "2022-11-01T11:00:06Z"
  },
  {
    "topic": "technology",
    "title": "Old Or New Technology?",
    "videoId": "uvG-WToQfU4",
    "thumbnail": "https://i.ytimg.com/vi/uvG-WToQfU4/mqdefault.jpg",
    "publishedAt": "2024-07-17T19:15:02Z"
  },
  {
    "topic": "technology",
    "title": "With technology anything is possible, canalization cleanup techniques and technology #innovation",
    "videoId": "B-8fnn-aRuQ",
    "thumbnail": "https://i.ytimg.com/vi/B-8fnn-aRuQ/mqdefault.jpg",
    "publishedAt": "2023-02-28T13:55:59Z"
  },
  {
    "topic": "technology",
    "title": "iShowSpeed Shocked By This Technology In China 🤯🔥",
    "videoId": "g8DA2e0LoIw",
    "thumbnail": "https://i.ytimg.com/vi/g8DA2e0LoIw/mqdefault.jpg",
    "publishedAt": "2025-04-01T14:28:05Z"
  }
]